README.md
setup.py
SkyHyveLM/SkyHyveLM.py
SkyHyveLM/__init__.py
SkyHyveLM.egg-info/PKG-INFO
SkyHyveLM.egg-info/SOURCES.txt
SkyHyveLM.egg-info/dependency_links.txt
SkyHyveLM.egg-info/top_level.txt