Metadata-Version: 1.0
Name: SkyHyveLM
Version: 0.1
Summary: Wrapper for large socket communications
Home-page: https://github.com/ThePengwyn/SkyHyveLM
Author: Matthew Graham
Author-email: matthewg@skyhyve.xyz
License: MIT
Platform: UNKNOWN
